pyW215/__init__.py
pyW215/pyW215.py
pyw215-0.8.0.dist-info/METADATA
pyw215-0.8.0.dist-info/WHEEL
pyw215-0.8.0.dist-info/top_level.txt
pyw215-0.8.0.dist-info/RECORD
