Metadata-Version: 2.4
Name: pyW215
Version: 0.8.0
Summary: Interface for d-link W215 Smart Plugs.
Home-page: https://github.com/linuxchristian/pyW215
Author: Christian Juncker Brædstrup
Author-email: christian@junckerbraedstrup.dk
License: MIT
Keywords: D-Link W215 W110 Smartplug
Dynamic: author
Dynamic: author-email
Dynamic: description
Dynamic: home-page
Dynamic: keywords
Dynamic: license
Dynamic: summary
